scatteringmatrix/__init__.py
scatteringmatrix/indexfunc.py
scatteringmatrix/scatteringmatrix.py
scatteringmatrix/smfileload.py
scatteringmatrix/units.py
scatteringmatrix-0.1.0.dev6.dist-info/LICENSE.txt
scatteringmatrix-0.1.0.dev6.dist-info/METADATA
scatteringmatrix-0.1.0.dev6.dist-info/WHEEL
scatteringmatrix-0.1.0.dev6.dist-info/top_level.txt
scatteringmatrix-0.1.0.dev6.dist-info/RECORD
