Metadata-Version: 2.1
Name: scatteringmatrix
Version: 0.1.0.dev6
Summary: Optical scattering matrix library
Home-page: https://github.com/agflood/scatteringmatrix
Author: Andrew G. Flood
Author-email: andrew.gary.flood@gmail.com
License: MIT
Keywords: optics scattering matrix photonics
Platform: UNKNOWN
Classifier: Development Status :: 2 - Pre-Alpha
Classifier: Intended Audience :: Science/Research
Classifier: Topic :: Scientific/Engineering
Classifier: License :: OSI Approved :: MIT License
Classifier: Programming Language :: Python :: 3
Classifier: Programming Language :: Python :: 3.2
Classifier: Programming Language :: Python :: 3.3
Classifier: Programming Language :: Python :: 3.4
Classifier: Programming Language :: Python :: 3.5
Classifier: Programming Language :: Python :: 3.6
Requires-Python: >=3
Requires-Dist: numpy
Requires-Dist: scipy
